tm_timer/__init__.py
tm_timer/cli.py
tm_timer-2.0.dist-info/licenses/LICENSE
tm_timer-2.0.dist-info/METADATA
tm_timer-2.0.dist-info/WHEEL
tm_timer-2.0.dist-info/entry_points.txt
tm_timer-2.0.dist-info/top_level.txt
tm_timer-2.0.dist-info/RECORD
