Metadata-Version: 2.4
Name: tm-timer
Version: 2.0
Summary: Minimalistic terminal-based timer with Study/Train tracking
Author: ph4nt01
Author-email: Ph4nt01 <ph4nt0.84@email.com>
License: MIT
Requires-Python: >=3.6
License-File: LICENSE
Dynamic: author
Dynamic: license-file
Dynamic: requires-python
